setup.py
distributions_1pint/Binomialdistribution.py
distributions_1pint/Gaussiandistribution.py
distributions_1pint/Generaldistribution.py
distributions_1pint/__init__.py
distributions_1pint.egg-info/PKG-INFO
distributions_1pint.egg-info/SOURCES.txt
distributions_1pint.egg-info/dependency_links.txt
distributions_1pint.egg-info/not-zip-safe
distributions_1pint.egg-info/top_level.txt